{
    "datasource": {
        "type": "sqlite",
        "filename": "~/.susm/data/susm.db"
    },
    "log": {
        "filemode": "w",
        "filename": "~/.susm/log/suapp.log",
        "format": "%(asctime)s %(levelname)s %(name)s %(message)s",
        "level": "INFO",
        "modules": {
            "base": {
                "level": "INFO"
            },
            "httpd": {
                "filename": "~/.susm/log/httpd.accces_log",
                "level": "DEBUG"
            }
        }
    },
    "modules": {
        "base": {},
        "kinship": {
            "method": "pc"
        },
        "location": {}
    },
    "name": "SU Stud Manager",
    "shortname": "SuSM"
}
